{
    "@id": "https://brambg.github.io/static-file-server/globalise/1061/iiif-annotations-NL-HaNA_1.04.02_1061_0649.json",
    "@context": "http://iiif.io/api/presentation/2/context.json",
    "@type": "sc:AnnotationList",
    "resources": [
        {
            "@id": "urn:globalise:annotation:af22c47f-d6b2-4ef0-b68c-cf9b285494e5",
            "@type": "oa:Annotation",
            "motivation": [
                "oa:commenting",
                "oa:Tagging"
            ],
            "on": [
                {
                    "@type": "oa:SpecificResource",
                    "full": "https://data.globalise.huygens.knaw.nl/manifests/inventories/1061.json/canvas/p649",
                    "selector": {
                        "@type": "oa:Choice",
                        "default": {
                            "@type": "oa:FragmentSelector",
                            "value": "xywh=1679,394,142,48"
                        },
                        "item": {
                            "@type": "oa:SvgSelector",
                            "value": "<svg height=\"442\" width=\"1821\"><path d=\"M1680 397 L1681 397 L1730 397 L1779 395 L1820 394 L1821 439 L1780 440 L1730 442 L1680 442 L1679 442 Z\"/></svg>"
                        }
                    },
                    "within": {
                        "@id": "h",
                        "@type": "sc:Manifest"
                    }
                }
            ],
            "resource": [
                {
                    "@type": "dctypes:Text",
                    "format": "text/html",
                    "chars": "Reyse"
                },
                {
                    "@type": "oa:Tag",
                    "format": "text/html",
                    "chars": "Location"
                }
            ]
        },
        {
            "@id": "urn:globalise:annotation:1ff4e5fa-871d-4de3-aa92-88ef57ea4f0e",
            "@type": "oa:Annotation",
            "motivation": [
                "oa:commenting",
                "oa:Tagging"
            ],
            "on": [
                {
                    "@type": "oa:SpecificResource",
                    "full": "https://data.globalise.huygens.knaw.nl/manifests/inventories/1061.json/canvas/p649",
                    "selector": {
                        "@type": "oa:Choice",
                        "default": {
                            "@type": "oa:FragmentSelector",
                            "value": "xywh=528,447,218,49"
                        },
                        "item": {
                            "@type": "oa:SvgSelector",
                            "value": "<svg height=\"496\" width=\"746\"><path d=\"M532 447 L582 451 L628 450 L679 450 L729 450 L745 450 L746 495 L729 495 L679 495 L629 495 L578 496 L528 492 Z\"/></svg>"
                        }
                    },
                    "within": {
                        "@id": "h",
                        "@type": "sc:Manifest"
                    }
                }
            ],
            "resource": [
                {
                    "@type": "dctypes:Text",
                    "format": "text/html",
                    "chars": "vlagghe"
                },
                {
                    "@type": "oa:Tag",
                    "format": "text/html",
                    "chars": "Commodity"
                }
            ]
        },
        {
            "@id": "urn:globalise:annotation:a10ef437-154a-466b-9a55-d865e478c18f",
            "@type": "oa:Annotation",
            "motivation": [
                "oa:commenting",
                "oa:Tagging"
            ],
            "on": [
                {
                    "@type": "oa:SpecificResource",
                    "full": "https://data.globalise.huygens.knaw.nl/manifests/inventories/1061.json/canvas/p649",
                    "selector": {
                        "@type": "oa:Choice",
                        "default": {
                            "@type": "oa:FragmentSelector",
                            "value": "xywh=1378,561,144,48"
                        },
                        "item": {
                            "@type": "oa:SvgSelector",
                            "value": "<svg height=\"609\" width=\"1522\"><path d=\"M1378 564 L1421 564 L1470 562 L1520 561 L1520 561 L1522 606 L1521 606 L1471 607 L1421 609 L1378 609 Z\"/></svg>"
                        }
                    },
                    "within": {
                        "@id": "h",
                        "@type": "sc:Manifest"
                    }
                }
            ],
            "resource": [
                {
                    "@type": "dctypes:Text",
                    "format": "text/html",
                    "chars": "lanck"
                },
                {
                    "@type": "oa:Tag",
                    "format": "text/html",
                    "chars": "Commodity"
                }
            ]
        },
        {
            "@id": "urn:globalise:annotation:e12abbd0-e996-487e-8dcc-376c08da4630",
            "@type": "oa:Annotation",
            "motivation": [
                "oa:commenting",
                "oa:Tagging"
            ],
            "on": [
                {
                    "@type": "oa:SpecificResource",
                    "full": "https://data.globalise.huygens.knaw.nl/manifests/inventories/1061.json/canvas/p649",
                    "selector": {
                        "@type": "oa:Choice",
                        "default": {
                            "@type": "oa:FragmentSelector",
                            "value": "xywh=2263,540,230,50"
                        },
                        "item": {
                            "@type": "oa:SvgSelector",
                            "value": "<svg height=\"590\" width=\"2493\"><path d=\"M2263 545 L2270 545 L2320 543 L2370 542 L2420 541 L2470 540 L2492 540 L2493 585 L2471 585 L2421 586 L2371 587 L2321 588 L2271 590 L2265 590 Z\"/></svg>"
                        }
                    },
                    "within": {
                        "@id": "h",
                        "@type": "sc:Manifest"
                    }
                }
            ],
            "resource": [
                {
                    "@type": "dctypes:Text",
                    "format": "text/html",
                    "chars": "Comptoir"
                },
                {
                    "@type": "oa:Tag",
                    "format": "text/html",
                    "chars": "Profession"
                }
            ]
        },
        {
            "@id": "urn:globalise:annotation:ace55c93-4184-45ab-99ff-081312df5039",
            "@type": "oa:Annotation",
            "motivation": [
                "oa:commenting",
                "oa:Tagging"
            ],
            "on": [
                {
                    "@type": "oa:SpecificResource",
                    "full": "https://data.globalise.huygens.knaw.nl/manifests/inventories/1061.json/canvas/p649",
                    "selector": {
                        "@type": "oa:Choice",
                        "default": {
                            "@type": "oa:FragmentSelector",
                            "value": "xywh=533,628,181,48"
                        },
                        "item": {
                            "@type": "oa:SvgSelector",
                            "value": "<svg height=\"676\" width=\"714\"><path d=\"M533 631 L583 630 L633 629 L683 628 L714 628 L714 673 L684 673 L634 674 L584 675 L534 676 Z\"/></svg>"
                        }
                    },
                    "within": {
                        "@id": "h",
                        "@type": "sc:Manifest"
                    }
                }
            ],
            "resource": [
                {
                    "@type": "dctypes:Text",
                    "format": "text/html",
                    "chars": "Jambij"
                },
                {
                    "@type": "oa:Tag",
                    "format": "text/html",
                    "chars": "Location"
                }
            ]
        },
        {
            "@id": "urn:globalise:annotation:00548d3a-1dc7-4783-a84a-f39a23a0cee4",
            "@type": "oa:Annotation",
            "motivation": [
                "oa:commenting",
                "oa:Tagging"
            ],
            "on": [
                {
                    "@type": "oa:SpecificResource",
                    "full": "https://data.globalise.huygens.knaw.nl/manifests/inventories/1061.json/canvas/p649",
                    "selector": {
                        "@type": "oa:Choice",
                        "default": {
                            "@type": "oa:FragmentSelector",
                            "value": "xywh=862,624,61,48"
                        },
                        "item": {
                            "@type": "oa:SvgSelector",
                            "value": "<svg height=\"672\" width=\"1284\"><path d=\"M862 627 L882 626 L922 624 L923 669 L884 671 L864 672 Z M950 623 L981 621 L1033 620 L1084 620 L1102 620 L1103 665 L1084 665 L1034 665 L985 666 L954 668 Z M1132 619 L1133 619 L1185 621 L1235 622 L1284 625 L1281 670 L1234 667 L1184 666 L1134 664 L1133 664 Z\"/></svg>"
                        }
                    },
                    "within": {
                        "@id": "h",
                        "@type": "sc:Manifest"
                    }
                }
            ],
            "resource": [
                {
                    "@type": "dctypes:Text",
                    "format": "text/html",
                    "chars": "30 Junij 1616"
                },
                {
                    "@type": "oa:Tag",
                    "format": "text/html",
                    "chars": "Date"
                }
            ]
        },
        {
            "@id": "urn:globalise:annotation:ca204708-ecf8-4db7-9fcf-91657148259b",
            "@type": "oa:Annotation",
            "motivation": [
                "oa:commenting",
                "oa:Tagging"
            ],
            "on": [
                {
                    "@type": "oa:SpecificResource",
                    "full": "https://data.globalise.huygens.knaw.nl/manifests/inventories/1061.json/canvas/p649",
                    "selector": {
                        "@type": "oa:Choice",
                        "default": {
                            "@type": "oa:FragmentSelector",
                            "value": "xywh=1848,604,62,48"
                        },
                        "item": {
                            "@type": "oa:SvgSelector",
                            "value": "<svg height=\"652\" width=\"2000\"><path d=\"M1848 607 L1882 605 L1908 604 L1910 649 L1884 650 L1851 652 Z M1939 603 L1983 602 L1999 602 L2000 647 L1984 647 L1940 648 Z\"/></svg>"
                        }
                    },
                    "within": {
                        "@id": "h",
                        "@type": "sc:Manifest"
                    }
                }
            ],
            "resource": [
                {
                    "@type": "dctypes:Text",
                    "format": "text/html",
                    "chars": "V. E."
                },
                {
                    "@type": "oa:Tag",
                    "format": "text/html",
                    "chars": "Organisation"
                }
            ]
        },
        {
            "@id": "urn:globalise:annotation:b6ebfbfa-0b02-4e76-bffa-aa41ef35bc17",
            "@type": "oa:Annotation",
            "motivation": [
                "oa:commenting",
                "oa:Tagging"
            ],
            "on": [
                {
                    "@type": "oa:SpecificResource",
                    "full": "https://data.globalise.huygens.knaw.nl/manifests/inventories/1061.json/canvas/p649",
                    "selector": {
                        "@type": "oa:Choice",
                        "default": {
                            "@type": "oa:FragmentSelector",
                            "value": "xywh=1427,703,296,56"
                        },
                        "item": {
                            "@type": "oa:SvgSelector",
                            "value": "<svg height=\"882\" width=\"2018\"><path d=\"M1428 713 L1478 714 L1524 710 L1575 707 L1626 705 L1676 704 L1722 703 L1723 748 L1677 749 L1627 750 L1578 752 L1528 755 L1477 759 L1427 758 Z M1764 702 L1776 702 L1826 701 L1876 700 L1926 699 L1976 698 L2018 698 L2018 743 L1977 743 L1927 744 L1877 745 L1827 746 L1777 747 L1765 747 Z M486 829 L536 834 L584 836 L630 837 L629 882 L583 881 L532 879 L482 874 Z\"/></svg>"
                        }
                    },
                    "within": {
                        "@id": "h",
                        "@type": "sc:Manifest"
                    }
                }
            ],
            "resource": [
                {
                    "@type": "dctypes:Text",
                    "format": "text/html",
                    "chars": "Andries Sourij Drent"
                },
                {
                    "@type": "oa:Tag",
                    "format": "text/html",
                    "chars": "Person"
                }
            ]
        },
        {
            "@id": "urn:globalise:annotation:78217a40-e7ef-4431-927b-001d0273d803",
            "@type": "oa:Annotation",
            "motivation": [
                "oa:commenting",
                "oa:Tagging"
            ],
            "on": [
                {
                    "@type": "oa:SpecificResource",
                    "full": "https://data.globalise.huygens.knaw.nl/manifests/inventories/1061.json/canvas/p649",
                    "selector": {
                        "@type": "oa:Choice",
                        "default": {
                            "@type": "oa:FragmentSelector",
                            "value": "xywh=1619,948,219,46"
                        },
                        "item": {
                            "@type": "oa:SvgSelector",
                            "value": "<svg height=\"994\" width=\"1838\"><path d=\"M1619 949 L1637 949 L1688 949 L1738 949 L1787 948 L1838 948 L1838 993 L1788 993 L1738 994 L1688 994 L1638 994 L1620 994 Z\"/></svg>"
                        }
                    },
                    "within": {
                        "@id": "h",
                        "@type": "sc:Manifest"
                    }
                }
            ],
            "resource": [
                {
                    "@type": "dctypes:Text",
                    "format": "text/html",
                    "chars": "Schepen"
                },
                {
                    "@type": "oa:Tag",
                    "format": "text/html",
                    "chars": "Ship"
                }
            ]
        },
        {
            "@id": "urn:globalise:annotation:7bae7c15-adca-4b30-8a2e-0ba224114195",
            "@type": "oa:Annotation",
            "motivation": [
                "oa:commenting",
                "oa:Tagging"
            ],
            "on": [
                {
                    "@type": "oa:SpecificResource",
                    "full": "https://data.globalise.huygens.knaw.nl/manifests/inventories/1061.json/canvas/p649",
                    "selector": {
                        "@type": "oa:Choice",
                        "default": {
                            "@type": "oa:FragmentSelector",
                            "value": "xywh=512,1029,238,53"
                        },
                        "item": {
                            "@type": "oa:SvgSelector",
                            "value": "<svg height=\"1082\" width=\"750\"><path d=\"M512 1037 L562 1036 L612 1034 L662 1032 L712 1030 L749 1029 L750 1074 L713 1075 L663 1077 L613 1079 L563 1081 L513 1082 Z\"/></svg>"
                        }
                    },
                    "within": {
                        "@id": "h",
                        "@type": "sc:Manifest"
                    }
                }
            ],
            "resource": [
                {
                    "@type": "dctypes:Text",
                    "format": "text/html",
                    "chars": "Prauwken"
                },
                {
                    "@type": "oa:Tag",
                    "format": "text/html",
                    "chars": "Ship"
                }
            ]
        },
        {
            "@id": "urn:globalise:annotation:89dd81f3-6fc2-4915-92c6-16357cff6cac",
            "@type": "oa:Annotation",
            "motivation": [
                "oa:commenting",
                "oa:Tagging"
            ],
            "on": [
                {
                    "@type": "oa:SpecificResource",
                    "full": "https://data.globalise.huygens.knaw.nl/manifests/inventories/1061.json/canvas/p649",
                    "selector": {
                        "@type": "oa:Choice",
                        "default": {
                            "@type": "oa:FragmentSelector",
                            "value": "xywh=1278,1007,210,52"
                        },
                        "item": {
                            "@type": "oa:SvgSelector",
                            "value": "<svg height=\"1059\" width=\"1488\"><path d=\"M1278 1014 L1310 1011 L1362 1009 L1412 1007 L1463 1007 L1487 1007 L1488 1051 L1463 1052 L1413 1052 L1363 1054 L1314 1056 L1282 1059 Z\"/></svg>"
                        }
                    },
                    "within": {
                        "@id": "h",
                        "@type": "sc:Manifest"
                    }
                }
            ],
            "resource": [
                {
                    "@type": "dctypes:Text",
                    "format": "text/html",
                    "chars": "Coninck"
                },
                {
                    "@type": "oa:Tag",
                    "format": "text/html",
                    "chars": "Profession"
                }
            ]
        },
        {
            "@id": "urn:globalise:annotation:4bf16820-729e-4ae2-9648-9f49e7095fe0",
            "@type": "oa:Annotation",
            "motivation": [
                "oa:commenting",
                "oa:Tagging"
            ],
            "on": [
                {
                    "@type": "oa:SpecificResource",
                    "full": "https://data.globalise.huygens.knaw.nl/manifests/inventories/1061.json/canvas/p649",
                    "selector": {
                        "@type": "oa:Choice",
                        "default": {
                            "@type": "oa:FragmentSelector",
                            "value": "xywh=1635,1000,178,48"
                        },
                        "item": {
                            "@type": "oa:SvgSelector",
                            "value": "<svg height=\"1048\" width=\"1813\"><path d=\"M1635 1003 L1662 1002 L1712 1001 L1762 1000 L1813 1000 L1813 1000 L1813 1045 L1813 1045 L1763 1045 L1713 1046 L1663 1047 L1636 1048 Z\"/></svg>"
                        }
                    },
                    "within": {
                        "@id": "h",
                        "@type": "sc:Manifest"
                    }
                }
            ],
            "resource": [
                {
                    "@type": "dctypes:Text",
                    "format": "text/html",
                    "chars": "Jambij"
                },
                {
                    "@type": "oa:Tag",
                    "format": "text/html",
                    "chars": "Location"
                }
            ]
        },
        {
            "@id": "urn:globalise:annotation:e2202342-001d-4957-aa4b-de1d696f27f6",
            "@type": "oa:Annotation",
            "motivation": [
                "oa:commenting",
                "oa:Tagging"
            ],
            "on": [
                {
                    "@type": "oa:SpecificResource",
                    "full": "https://data.globalise.huygens.knaw.nl/manifests/inventories/1061.json/canvas/p649",
                    "selector": {
                        "@type": "oa:Choice",
                        "default": {
                            "@type": "oa:FragmentSelector",
                            "value": "xywh=1648,1179,176,52"
                        },
                        "item": {
                            "@type": "oa:SvgSelector",
                            "value": "<svg height=\"1231\" width=\"1824\"><path d=\"M1648 1187 L1669 1185 L1720 1183 L1770 1182 L1819 1179 L1822 1179 L1824 1224 L1822 1224 L1771 1227 L1721 1228 L1672 1230 L1651 1231 Z\"/></svg>"
                        }
                    },
                    "within": {
                        "@id": "h",
                        "@type": "sc:Manifest"
                    }
                }
            ],
            "resource": [
                {
                    "@type": "dctypes:Text",
                    "format": "text/html",
                    "chars": "Jambij"
                },
                {
                    "@type": "oa:Tag",
                    "format": "text/html",
                    "chars": "Location"
                }
            ]
        },
        {
            "@id": "urn:globalise:annotation:fdc2c4d2-5f01-431b-b551-80edc1b848c4",
            "@type": "oa:Annotation",
            "motivation": [
                "oa:commenting",
                "oa:Tagging"
            ],
            "on": [
                {
                    "@type": "oa:SpecificResource",
                    "full": "https://data.globalise.huygens.knaw.nl/manifests/inventories/1061.json/canvas/p649",
                    "selector": {
                        "@type": "oa:Choice",
                        "default": {
                            "@type": "oa:FragmentSelector",
                            "value": "xywh=2320,1280,284,56"
                        },
                        "item": {
                            "@type": "oa:SvgSelector",
                            "value": "<svg height=\"1336\" width=\"2604\"><path d=\"M2320 1291 L2327 1291 L2376 1288 L2427 1286 L2477 1284 L2527 1283 L2577 1281 L2603 1280 L2604 1325 L2578 1326 L2528 1328 L2478 1329 L2428 1331 L2379 1333 L2328 1336 L2321 1336 Z\"/></svg>"
                        }
                    },
                    "within": {
                        "@id": "h",
                        "@type": "sc:Manifest"
                    }
                }
            ],
            "resource": [
                {
                    "@type": "dctypes:Text",
                    "format": "text/html",
                    "chars": "portugese"
                },
                {
                    "@type": "oa:Tag",
                    "format": "text/html",
                    "chars": "Location"
                }
            ]
        },
        {
            "@id": "urn:globalise:annotation:ef621d2c-2012-4d04-bb6b-3e18680d5170",
            "@type": "oa:Annotation",
            "motivation": [
                "oa:commenting",
                "oa:Tagging"
            ],
            "on": [
                {
                    "@type": "oa:SpecificResource",
                    "full": "https://data.globalise.huygens.knaw.nl/manifests/inventories/1061.json/canvas/p649",
                    "selector": {
                        "@type": "oa:Choice",
                        "default": {
                            "@type": "oa:FragmentSelector",
                            "value": "xywh=503,1771,293,61"
                        },
                        "item": {
                            "@type": "oa:SvgSelector",
                            "value": "<svg height=\"1832\" width=\"796\"><path d=\"M503 1787 L553 1782 L604 1779 L655 1777 L705 1775 L755 1773 L794 1771 L796 1816 L756 1818 L706 1820 L656 1822 L607 1824 L557 1827 L507 1832 Z\"/></svg>"
                        }
                    },
                    "within": {
                        "@id": "h",
                        "@type": "sc:Manifest"
                    }
                }
            ],
            "resource": [
                {
                    "@type": "dctypes:Text",
                    "format": "text/html",
                    "chars": "portugesen"
                },
                {
                    "@type": "oa:Tag",
                    "format": "text/html",
                    "chars": "Location"
                }
            ]
        },
        {
            "@id": "urn:globalise:annotation:cf99d48d-5360-4ba2-9869-ad4caf4d34db",
            "@type": "oa:Annotation",
            "motivation": [
                "oa:commenting",
                "oa:Tagging"
            ],
            "on": [
                {
                    "@type": "oa:SpecificResource",
                    "full": "https://data.globalise.huygens.knaw.nl/manifests/inventories/1061.json/canvas/p649",
                    "selector": {
                        "@type": "oa:Choice",
                        "default": {
                            "@type": "oa:FragmentSelector",
                            "value": "xywh=2344,1948,238,49"
                        },
                        "item": {
                            "@type": "oa:SvgSelector",
                            "value": "<svg height=\"1997\" width=\"2582\"><path d=\"M2344 1952 L2383 1950 L2433 1949 L2484 1949 L2533 1948 L2582 1950 L2580 1995 L2534 1993 L2484 1994 L2434 1994 L2384 1995 L2346 1997 Z\"/></svg>"
                        }
                    },
                    "within": {
                        "@id": "h",
                        "@type": "sc:Manifest"
                    }
                }
            ],
            "resource": [
                {
                    "@type": "dctypes:Text",
                    "format": "text/html",
                    "chars": "Chinnes"
                },
                {
                    "@type": "oa:Tag",
                    "format": "text/html",
                    "chars": "Location"
                }
            ]
        },
        {
            "@id": "urn:globalise:annotation:9cff7ed4-ca39-4cc7-b759-9d93f71398da",
            "@type": "oa:Annotation",
            "motivation": [
                "oa:commenting",
                "oa:Tagging"
            ],
            "on": [
                {
                    "@type": "oa:SpecificResource",
                    "full": "https://data.globalise.huygens.knaw.nl/manifests/inventories/1061.json/canvas/p649",
                    "selector": {
                        "@type": "oa:Choice",
                        "default": {
                            "@type": "oa:FragmentSelector",
                            "value": "xywh=1192,2293,322,51"
                        },
                        "item": {
                            "@type": "oa:SvgSelector",
                            "value": "<svg height=\"2344\" width=\"1514\"><path d=\"M1192 2299 L1219 2298 L1269 2297 L1320 2297 L1369 2296 L1419 2295 L1469 2293 L1514 2293 L1514 2338 L1470 2338 L1420 2340 L1370 2341 L1320 2342 L1270 2342 L1220 2343 L1194 2344 Z\"/></svg>"
                        }
                    },
                    "within": {
                        "@id": "h",
                        "@type": "sc:Manifest"
                    }
                }
            ],
            "resource": [
                {
                    "@type": "dctypes:Text",
                    "format": "text/html",
                    "chars": "portugesen"
                },
                {
                    "@type": "oa:Tag",
                    "format": "text/html",
                    "chars": "Location"
                }
            ]
        },
        {
            "@id": "urn:globalise:annotation:a0ed580e-3cb2-4412-afa7-ed86db17b3a6",
            "@type": "oa:Annotation",
            "motivation": [
                "oa:commenting",
                "oa:Tagging"
            ],
            "on": [
                {
                    "@type": "oa:SpecificResource",
                    "full": "https://data.globalise.huygens.knaw.nl/manifests/inventories/1061.json/canvas/p649",
                    "selector": {
                        "@type": "oa:Choice",
                        "default": {
                            "@type": "oa:FragmentSelector",
                            "value": "xywh=2153,2330,192,50"
                        },
                        "item": {
                            "@type": "oa:SvgSelector",
                            "value": "<svg height=\"2380\" width=\"2345\"><path d=\"M2153 2335 L2171 2334 L2221 2332 L2271 2331 L2321 2330 L2345 2330 L2345 2375 L2322 2375 L2272 2376 L2222 2377 L2172 2379 L2155 2380 Z\"/></svg>"
                        }
                    },
                    "within": {
                        "@id": "h",
                        "@type": "sc:Manifest"
                    }
                }
            ],
            "resource": [
                {
                    "@type": "dctypes:Text",
                    "format": "text/html",
                    "chars": "Coninck"
                },
                {
                    "@type": "oa:Tag",
                    "format": "text/html",
                    "chars": "Profession"
                }
            ]
        },
        {
            "@id": "urn:globalise:annotation:bd27495f-0b49-460f-9464-aaded66f6b2e",
            "@type": "oa:Annotation",
            "motivation": [
                "oa:commenting",
                "oa:Tagging"
            ],
            "on": [
                {
                    "@type": "oa:SpecificResource",
                    "full": "https://data.globalise.huygens.knaw.nl/manifests/inventories/1061.json/canvas/p649",
                    "selector": {
                        "@type": "oa:Choice",
                        "default": {
                            "@type": "oa:FragmentSelector",
                            "value": "xywh=915,2729,319,53"
                        },
                        "item": {
                            "@type": "oa:SvgSelector",
                            "value": "<svg height=\"2782\" width=\"1234\"><path d=\"M915 2737 L951 2735 L1002 2734 L1052 2732 L1102 2731 L1152 2730 L1203 2730 L1234 2729 L1234 2774 L1203 2775 L1153 2775 L1103 2776 L1053 2777 L1003 2779 L953 2780 L917 2782 Z\"/></svg>"
                        }
                    },
                    "within": {
                        "@id": "h",
                        "@type": "sc:Manifest"
                    }
                }
            ],
            "resource": [
                {
                    "@type": "dctypes:Text",
                    "format": "text/html",
                    "chars": "portugesen"
                },
                {
                    "@type": "oa:Tag",
                    "format": "text/html",
                    "chars": "Location"
                }
            ]
        },
        {
            "@id": "urn:globalise:annotation:fd70201a-8d1c-4bc9-b9ea-2a42a823d846",
            "@type": "oa:Annotation",
            "motivation": [
                "oa:commenting",
                "oa:Tagging"
            ],
            "on": [
                {
                    "@type": "oa:SpecificResource",
                    "full": "https://data.globalise.huygens.knaw.nl/manifests/inventories/1061.json/canvas/p649",
                    "selector": {
                        "@type": "oa:Choice",
                        "default": {
                            "@type": "oa:FragmentSelector",
                            "value": "xywh=1285,2838,289,52"
                        },
                        "item": {
                            "@type": "oa:SvgSelector",
                            "value": "<svg height=\"2890\" width=\"1574\"><path d=\"M1285 2846 L1308 2844 L1359 2842 L1409 2841 L1459 2840 L1509 2839 L1559 2838 L1574 2838 L1574 2883 L1560 2883 L1510 2884 L1460 2885 L1410 2886 L1360 2887 L1311 2889 L1287 2890 Z\"/></svg>"
                        }
                    },
                    "within": {
                        "@id": "h",
                        "@type": "sc:Manifest"
                    }
                }
            ],
            "resource": [
                {
                    "@type": "dctypes:Text",
                    "format": "text/html",
                    "chars": "portugesen"
                },
                {
                    "@type": "oa:Tag",
                    "format": "text/html",
                    "chars": "Location"
                }
            ]
        },
        {
            "@id": "urn:globalise:annotation:6f20ac6c-c627-4d61-99a6-4f6855fb3032",
            "@type": "oa:Annotation",
            "motivation": [
                "oa:commenting",
                "oa:Tagging"
            ],
            "on": [
                {
                    "@type": "oa:SpecificResource",
                    "full": "https://data.globalise.huygens.knaw.nl/manifests/inventories/1061.json/canvas/p649",
                    "selector": {
                        "@type": "oa:Choice",
                        "default": {
                            "@type": "oa:FragmentSelector",
                            "value": "xywh=1716,2832,146,50"
                        },
                        "item": {
                            "@type": "oa:SvgSelector",
                            "value": "<svg height=\"2882\" width=\"1862\"><path d=\"M1716 2837 L1758 2835 L1809 2833 L1859 2832 L1861 2832 L1862 2877 L1860 2877 L1810 2878 L1761 2880 L1719 2882 Z\"/></svg>"
                        }
                    },
                    "within": {
                        "@id": "h",
                        "@type": "sc:Manifest"
                    }
                }
            ],
            "resource": [
                {
                    "@type": "dctypes:Text",
                    "format": "text/html",
                    "chars": "bonen"
                },
                {
                    "@type": "oa:Tag",
                    "format": "text/html",
                    "chars": "Commodity"
                }
            ]
        },
        {
            "@id": "urn:globalise:annotation:9ac62e8b-b6ed-46ae-aeea-95c8768cf732",
            "@type": "oa:Annotation",
            "motivation": [
                "oa:commenting",
                "oa:Tagging"
            ],
            "on": [
                {
                    "@type": "oa:SpecificResource",
                    "full": "https://data.globalise.huygens.knaw.nl/manifests/inventories/1061.json/canvas/p649",
                    "selector": {
                        "@type": "oa:Choice",
                        "default": {
                            "@type": "oa:FragmentSelector",
                            "value": "xywh=2033,2829,204,46"
                        },
                        "item": {
                            "@type": "oa:SvgSelector",
                            "value": "<svg height=\"2875\" width=\"2237\"><path d=\"M2033 2830 L2059 2829 L2110 2829 L2160 2829 L2210 2829 L2237 2830 L2236 2875 L2210 2874 L2160 2874 L2110 2874 L2060 2874 L2035 2875 Z\"/></svg>"
                        }
                    },
                    "within": {
                        "@id": "h",
                        "@type": "sc:Manifest"
                    }
                }
            ],
            "resource": [
                {
                    "@type": "dctypes:Text",
                    "format": "text/html",
                    "chars": "Sterck"
                },
                {
                    "@type": "oa:Tag",
                    "format": "text/html",
                    "chars": "Location"
                }
            ]
        },
        {
            "@id": "urn:globalise:annotation:6c4ea015-3a9a-44f1-b033-8e73522a2236",
            "@type": "oa:Annotation",
            "motivation": [
                "oa:commenting",
                "oa:Tagging"
            ],
            "on": [
                {
                    "@type": "oa:SpecificResource",
                    "full": "https://data.globalise.huygens.knaw.nl/manifests/inventories/1061.json/canvas/p649",
                    "selector": {
                        "@type": "oa:Choice",
                        "default": {
                            "@type": "oa:FragmentSelector",
                            "value": "xywh=432,2978,93,47"
                        },
                        "item": {
                            "@type": "oa:SvgSelector",
                            "value": "<svg height=\"3026\" width=\"737\"><path d=\"M432 2980 L482 2978 L525 2980 L524 3025 L483 3023 L433 3025 Z M553 2981 L582 2980 L632 2979 L683 2979 L733 2979 L735 2979 L737 3024 L733 3024 L683 3024 L633 3024 L583 3025 L554 3026 Z\"/></svg>"
                        }
                    },
                    "within": {
                        "@id": "h",
                        "@type": "sc:Manifest"
                    }
                }
            ],
            "resource": [
                {
                    "@type": "dctypes:Text",
                    "format": "text/html",
                    "chars": "Van gelyck"
                },
                {
                    "@type": "oa:Tag",
                    "format": "text/html",
                    "chars": "Person"
                }
            ]
        },
        {
            "@id": "urn:globalise:annotation:c0d42739-8025-4e8c-8ee2-bf3c47e79518",
            "@type": "oa:Annotation",
            "motivation": [
                "oa:commenting",
                "oa:Tagging"
            ],
            "on": [
                {
                    "@type": "oa:SpecificResource",
                    "full": "https://data.globalise.huygens.knaw.nl/manifests/inventories/1061.json/canvas/p649",
                    "selector": {
                        "@type": "oa:Choice",
                        "default": {
                            "@type": "oa:FragmentSelector",
                            "value": "xywh=1402,2968,275,48"
                        },
                        "item": {
                            "@type": "oa:SvgSelector",
                            "value": "<svg height=\"3016\" width=\"1677\"><path d=\"M1402 2971 L1432 2970 L1483 2970 L1533 2970 L1582 2968 L1633 2968 L1677 2969 L1676 3014 L1633 3013 L1583 3013 L1533 3015 L1483 3015 L1433 3015 L1403 3016 Z\"/></svg>"
                        }
                    },
                    "within": {
                        "@id": "h",
                        "@type": "sc:Manifest"
                    }
                }
            ],
            "resource": [
                {
                    "@type": "dctypes:Text",
                    "format": "text/html",
                    "chars": "Andregaij"
                },
                {
                    "@type": "oa:Tag",
                    "format": "text/html",
                    "chars": "Location"
                }
            ]
        },
        {
            "@id": "urn:globalise:annotation:8826b6b6-5833-400a-83e6-8005bf67b77d",
            "@type": "oa:Annotation",
            "motivation": [
                "oa:commenting",
                "oa:Tagging"
            ],
            "on": [
                {
                    "@type": "oa:SpecificResource",
                    "full": "https://data.globalise.huygens.knaw.nl/manifests/inventories/1061.json/canvas/p649",
                    "selector": {
                        "@type": "oa:Choice",
                        "default": {
                            "@type": "oa:FragmentSelector",
                            "value": "xywh=1391,3077,308,52"
                        },
                        "item": {
                            "@type": "oa:SvgSelector",
                            "value": "<svg height=\"3129\" width=\"1699\"><path d=\"M1391 3084 L1400 3084 L1450 3083 L1500 3082 L1550 3081 L1600 3079 L1650 3078 L1698 3077 L1699 3122 L1651 3123 L1601 3124 L1551 3126 L1501 3127 L1451 3128 L1401 3129 L1392 3129 Z\"/></svg>"
                        }
                    },
                    "within": {
                        "@id": "h",
                        "@type": "sc:Manifest"
                    }
                }
            ],
            "resource": [
                {
                    "@type": "dctypes:Text",
                    "format": "text/html",
                    "chars": "Oortugesen"
                },
                {
                    "@type": "oa:Tag",
                    "format": "text/html",
                    "chars": "Location"
                }
            ]
        },
        {
            "@id": "urn:globalise:annotation:39b93738-c943-431a-96c0-0772af77e7e4",
            "@type": "oa:Annotation",
            "motivation": [
                "oa:commenting",
                "oa:Tagging"
            ],
            "on": [
                {
                    "@type": "oa:SpecificResource",
                    "full": "https://data.globalise.huygens.knaw.nl/manifests/inventories/1061.json/canvas/p649",
                    "selector": {
                        "@type": "oa:Choice",
                        "default": {
                            "@type": "oa:FragmentSelector",
                            "value": "xywh=506,3272,155,54"
                        },
                        "item": {
                            "@type": "oa:SvgSelector",
                            "value": "<svg height=\"3326\" width=\"661\"><path d=\"M506 3281 L556 3278 L606 3275 L656 3272 L659 3272 L661 3317 L659 3317 L609 3320 L559 3323 L509 3326 Z\"/></svg>"
                        }
                    },
                    "within": {
                        "@id": "h",
                        "@type": "sc:Manifest"
                    }
                }
            ],
            "resource": [
                {
                    "@type": "dctypes:Text",
                    "format": "text/html",
                    "chars": "Desen"
                },
                {
                    "@type": "oa:Tag",
                    "format": "text/html",
                    "chars": "Profession"
                }
            ]
        },
        {
            "@id": "urn:globalise:annotation:b8ec164a-ece1-4d25-a81d-7c8e38b5964b",
            "@type": "oa:Annotation",
            "motivation": [
                "oa:commenting",
                "oa:Tagging"
            ],
            "on": [
                {
                    "@type": "oa:SpecificResource",
                    "full": "https://data.globalise.huygens.knaw.nl/manifests/inventories/1061.json/canvas/p649",
                    "selector": {
                        "@type": "oa:Choice",
                        "default": {
                            "@type": "oa:FragmentSelector",
                            "value": "xywh=690,3266,215,50"
                        },
                        "item": {
                            "@type": "oa:SvgSelector",
                            "value": "<svg height=\"3316\" width=\"905\"><path d=\"M690 3271 L707 3270 L757 3269 L808 3269 L857 3267 L904 3266 L905 3311 L858 3312 L808 3314 L758 3314 L708 3315 L692 3316 Z\"/></svg>"
                        }
                    },
                    "within": {
                        "@id": "h",
                        "@type": "sc:Manifest"
                    }
                }
            ],
            "resource": [
                {
                    "@type": "dctypes:Text",
                    "format": "text/html",
                    "chars": "Coninck"
                },
                {
                    "@type": "oa:Tag",
                    "format": "text/html",
                    "chars": "Profession"
                }
            ]
        },
        {
            "@id": "urn:globalise:annotation:2a9ccf8f-ffe0-4c74-be76-9c0ed91ed701",
            "@type": "oa:Annotation",
            "motivation": [
                "oa:commenting",
                "oa:Tagging"
            ],
            "on": [
                {
                    "@type": "oa:SpecificResource",
                    "full": "https://data.globalise.huygens.knaw.nl/manifests/inventories/1061.json/canvas/p649",
                    "selector": {
                        "@type": "oa:Choice",
                        "default": {
                            "@type": "oa:FragmentSelector",
                            "value": "xywh=1264,3359,321,58"
                        },
                        "item": {
                            "@type": "oa:SvgSelector",
                            "value": "<svg height=\"3417\" width=\"1585\"><path d=\"M1264 3372 L1301 3369 L1354 3369 L1402 3366 L1452 3363 L1503 3361 L1553 3360 L1583 3359 L1585 3404 L1554 3405 L1504 3406 L1455 3408 L1405 3411 L1354 3414 L1305 3414 L1267 3417 Z\"/></svg>"
                        }
                    },
                    "within": {
                        "@id": "h",
                        "@type": "sc:Manifest"
                    }
                }
            ],
            "resource": [
                {
                    "@type": "dctypes:Text",
                    "format": "text/html",
                    "chars": "Oortugesen"
                },
                {
                    "@type": "oa:Tag",
                    "format": "text/html",
                    "chars": "Location"
                }
            ]
        },
        {
            "@id": "urn:globalise:annotation:6297ed2d-4bdf-4dc0-b8ad-d3c47203f171",
            "@type": "oa:Annotation",
            "motivation": [
                "oa:commenting",
                "oa:Tagging"
            ],
            "on": [
                {
                    "@type": "oa:SpecificResource",
                    "full": "https://data.globalise.huygens.knaw.nl/manifests/inventories/1061.json/canvas/p649",
                    "selector": {
                        "@type": "oa:Choice",
                        "default": {
                            "@type": "oa:FragmentSelector",
                            "value": "xywh=1504,3411,371,56"
                        },
                        "item": {
                            "@type": "oa:SvgSelector",
                            "value": "<svg height=\"3467\" width=\"1875\"><path d=\"M1504 3422 L1511 3422 L1561 3420 L1611 3419 L1662 3419 L1711 3417 L1761 3415 L1811 3413 L1861 3411 L1874 3411 L1875 3455 L1862 3456 L1812 3458 L1762 3460 L1712 3462 L1662 3464 L1612 3464 L1562 3465 L1512 3467 L1506 3467 Z\"/></svg>"
                        }
                    },
                    "within": {
                        "@id": "h",
                        "@type": "sc:Manifest"
                    }
                }
            ],
            "resource": [
                {
                    "@type": "dctypes:Text",
                    "format": "text/html",
                    "chars": "kerckmeesters"
                },
                {
                    "@type": "oa:Tag",
                    "format": "text/html",
                    "chars": "Profession"
                }
            ]
        },
        {
            "@id": "urn:globalise:annotation:8ea13e81-6e85-4406-8233-7d7eb08ac1b2",
            "@type": "oa:Annotation",
            "motivation": [
                "oa:commenting",
                "oa:Tagging"
            ],
            "on": [
                {
                    "@type": "oa:SpecificResource",
                    "full": "https://data.globalise.huygens.knaw.nl/manifests/inventories/1061.json/canvas/p649",
                    "selector": {
                        "@type": "oa:Choice",
                        "default": {
                            "@type": "oa:FragmentSelector",
                            "value": "xywh=507,3567,167,47"
                        },
                        "item": {
                            "@type": "oa:SvgSelector",
                            "value": "<svg height=\"3614\" width=\"674\"><path d=\"M507 3569 L557 3568 L607 3567 L658 3567 L673 3567 L674 3612 L658 3612 L608 3612 L558 3613 L508 3614 Z\"/></svg>"
                        }
                    },
                    "within": {
                        "@id": "h",
                        "@type": "sc:Manifest"
                    }
                }
            ],
            "resource": [
                {
                    "@type": "dctypes:Text",
                    "format": "text/html",
                    "chars": "sonnen"
                },
                {
                    "@type": "oa:Tag",
                    "format": "text/html",
                    "chars": "Commodity"
                }
            ]
        },
        {
            "@id": "urn:globalise:annotation:a6064abd-fbe0-47d1-934a-829fc8a5ef86",
            "@type": "oa:Annotation",
            "motivation": [
                "oa:commenting",
                "oa:Tagging"
            ],
            "on": [
                {
                    "@type": "oa:SpecificResource",
                    "full": "https://data.globalise.huygens.knaw.nl/manifests/inventories/1061.json/canvas/p649",
                    "selector": {
                        "@type": "oa:Choice",
                        "default": {
                            "@type": "oa:FragmentSelector",
                            "value": "xywh=920,3612,332,52"
                        },
                        "item": {
                            "@type": "oa:SvgSelector",
                            "value": "<svg height=\"3664\" width=\"1252\"><path d=\"M920 3619 L924 3619 L975 3619 L1024 3618 L1074 3616 L1126 3617 L1174 3615 L1224 3613 L1251 3612 L1252 3657 L1225 3658 L1175 3660 L1125 3662 L1075 3661 L1025 3663 L975 3664 L925 3664 L922 3664 Z\"/></svg>"
                        }
                    },
                    "within": {
                        "@id": "h",
                        "@type": "sc:Manifest"
                    }
                }
            ],
            "resource": [
                {
                    "@type": "dctypes:Text",
                    "format": "text/html",
                    "chars": "portugesen"
                },
                {
                    "@type": "oa:Tag",
                    "format": "text/html",
                    "chars": "Location"
                }
            ]
        },
        {
            "@id": "urn:globalise:annotation:4a252a26-a9ff-448d-80b5-ad265c50d676",
            "@type": "oa:Annotation",
            "motivation": [
                "oa:commenting",
                "oa:Tagging"
            ],
            "on": [
                {
                    "@type": "oa:SpecificResource",
                    "full": "https://data.globalise.huygens.knaw.nl/manifests/inventories/1061.json/canvas/p649",
                    "selector": {
                        "@type": "oa:Choice",
                        "default": {
                            "@type": "oa:FragmentSelector",
                            "value": "xywh=2241,3567,134,48"
                        },
                        "item": {
                            "@type": "oa:SvgSelector",
                            "value": "<svg height=\"3740\" width=\"2541\"><path d=\"M2241 3570 L2274 3569 L2324 3568 L2374 3567 L2375 3612 L2325 3613 L2275 3614 L2243 3615 Z M2407 3566 L2424 3566 L2474 3565 L2524 3564 L2535 3562 L2541 3607 L2525 3609 L2475 3610 L2425 3611 L2408 3611 Z M500 3695 L550 3692 L601 3690 L651 3688 L701 3687 L717 3687 L717 3732 L702 3732 L652 3733 L602 3735 L553 3737 L503 3740 Z\"/></svg>"
                        }
                    },
                    "within": {
                        "@id": "h",
                        "@type": "sc:Manifest"
                    }
                }
            ],
            "resource": [
                {
                    "@type": "dctypes:Text",
                    "format": "text/html",
                    "chars": "Boot vant Berger"
                },
                {
                    "@type": "oa:Tag",
                    "format": "text/html",
                    "chars": "Ship"
                }
            ]
        },
        {
            "@id": "urn:globalise:annotation:ce29ce96-eff1-4de5-b06f-a4f52f7007e7",
            "@type": "oa:Annotation",
            "motivation": [
                "oa:commenting",
                "oa:Tagging"
            ],
            "on": [
                {
                    "@type": "oa:SpecificResource",
                    "full": "https://data.globalise.huygens.knaw.nl/manifests/inventories/1061.json/canvas/p649",
                    "selector": {
                        "@type": "oa:Choice",
                        "default": {
                            "@type": "oa:FragmentSelector",
                            "value": "xywh=1648,3640,361,60"
                        },
                        "item": {
                            "@type": "oa:SvgSelector",
                            "value": "<svg height=\"3700\" width=\"2009\"><path d=\"M1648 3655 L1650 3655 L1700 3652 L1751 3650 L1801 3649 L1851 3647 L1901 3645 L1951 3644 L1999 3640 L2007 3640 L2009 3685 L2003 3685 L1952 3689 L1902 3690 L1852 3692 L1802 3694 L1752 3695 L1703 3697 L1653 3700 L1651 3700 Z\"/></svg>"
                        }
                    },
                    "within": {
                        "@id": "h",
                        "@type": "sc:Manifest"
                    }
                }
            ],
            "resource": [
                {
                    "@type": "dctypes:Text",
                    "format": "text/html",
                    "chars": "valnibansl"
                },
                {
                    "@type": "oa:Tag",
                    "format": "text/html",
                    "chars": "Location"
                }
            ]
        },
        {
            "@id": "urn:globalise:annotation:f36c51ef-8ab5-4cec-a7ff-c9f35e9b10ac",
            "@type": "oa:Annotation",
            "motivation": [
                "oa:commenting",
                "oa:Tagging"
            ],
            "on": [
                {
                    "@type": "oa:SpecificResource",
                    "full": "https://data.globalise.huygens.knaw.nl/manifests/inventories/1061.json/canvas/p649",
                    "selector": {
                        "@type": "oa:Choice",
                        "default": {
                            "@type": "oa:FragmentSelector",
                            "value": "xywh=496,3745,300,57"
                        },
                        "item": {
                            "@type": "oa:SvgSelector",
                            "value": "<svg height=\"3802\" width=\"796\"><path d=\"M496 3757 L546 3755 L596 3753 L645 3750 L696 3749 L745 3746 L795 3745 L796 3790 L748 3791 L697 3794 L648 3795 L597 3798 L547 3800 L497 3802 Z\"/></svg>"
                        }
                    },
                    "within": {
                        "@id": "h",
                        "@type": "sc:Manifest"
                    }
                }
            ],
            "resource": [
                {
                    "@type": "dctypes:Text",
                    "format": "text/html",
                    "chars": "ambassado"
                },
                {
                    "@type": "oa:Tag",
                    "format": "text/html",
                    "chars": "Profession"
                }
            ]
        },
        {
            "@id": "urn:globalise:annotation:ca181189-db45-46a2-b1c6-59ee61d60b20",
            "@type": "oa:Annotation",
            "motivation": [
                "oa:commenting",
                "oa:Tagging"
            ],
            "on": [
                {
                    "@type": "oa:SpecificResource",
                    "full": "https://data.globalise.huygens.knaw.nl/manifests/inventories/1061.json/canvas/p649",
                    "selector": {
                        "@type": "oa:Choice",
                        "default": {
                            "@type": "oa:FragmentSelector",
                            "value": "xywh=1193,3725,235,52"
                        },
                        "item": {
                            "@type": "oa:SvgSelector",
                            "value": "<svg height=\"3777\" width=\"1428\"><path d=\"M1193 3732 L1196 3732 L1246 3731 L1296 3729 L1346 3728 L1396 3726 L1426 3725 L1428 3770 L1397 3771 L1347 3773 L1297 3774 L1247 3776 L1197 3777 L1195 3777 Z\"/></svg>"
                        }
                    },
                    "within": {
                        "@id": "h",
                        "@type": "sc:Manifest"
                    }
                }
            ],
            "resource": [
                {
                    "@type": "dctypes:Text",
                    "format": "text/html",
                    "chars": "Coninck"
                },
                {
                    "@type": "oa:Tag",
                    "format": "text/html",
                    "chars": "Profession"
                }
            ]
        }
    ]
}